lboxd_scraper/__init__.py
lboxd_scraper/lboxd.py
lboxd_scraper-0.0.7.dist-info/METADATA
lboxd_scraper-0.0.7.dist-info/WHEEL
lboxd_scraper-0.0.7.dist-info/licenses/LICENSE
lboxd_scraper-0.0.7.dist-info/RECORD
