Metadata-Version: 2.1
Name: lboxd_scraper
Version: 0.0.7
Summary: A package to help scrape letterboxd
Project-URL: Repository, https://github.com/lukegregorio/lboxd-scraper
Author-email: Luke Gregorio <author@example.com>
License-File: LICENSE
Classifier: License :: OSI Approved :: MIT License
Classifier: Operating System :: OS Independent
Classifier: Programming Language :: Python :: 3
Requires-Python: >=3.8
Requires-Dist: beautifulsoup4
